Experiment 01/boothMultiplier4Bit.v
module multiplier(prod, busy, mc, mp, clk, start);
    output reg [7:0] prod;
    output reg busy;
    input [3:0] mc, mp;
    input clk, start;
    reg [3:0] A, Q, M;
    reg Q_1;
    reg [2:0] count;
    wire [3:0] sum, difference;
    always @(posedge clk) begin
        if (start) begin
            A <= 0;
            M <= mc;
            Q <= mp;
            Q_1 <= 1'b0;
            count <= 0;
        end
        else begin
            busy <= 1'b1;
            case ({Q[0], Q_1})
                2'b0_1 : {A, Q, Q_1} <= {sum[3], sum, Q};
                2'b1_0 : {A, Q, Q_1} <= {difference[3], difference, Q};
                default: {A, Q, Q_1} <= {A[3], A, Q};
            endcase
            count <= count + 1'b1;
            if(count == 4) begin
                busy <= 1'b0;
                prod <= {A, Q};
                count <= 0;
            end
        end
    end
    alu adder (sum, A, M, 1'b0);
    alu subtracter (difference, A, ~M, 1'b1);
endmodule

//The following is an alu.
//It is an adder, but capable of subtraction:
//Recall that subtraction means adding the two's complement--
//a - b = a + (-b) = a + (inverted b + 1)
//The 1 will be coming in as cin (carry-in)
module alu(out, a, b, cin);
    output [3:0] out;
    input [3:0] a;
    input [3:0] b;
    input cin;
    assign out = a + b + cin;
endmodule

Experiment 01/boothMultiplier4Bit-testbench.v
`timescale 1ns/1ps

module testbench;
    //variables
    reg clk, start;
    reg [3:0] a, b;
    wire [7:0] ab;
    wire busy;
    integer i, j;
    //module instantiation
    multiplier uut(ab, busy, a, b, clk, start);
    //dump file generation - for non-ISE compilers
    initial begin
        $dumpfile("boothMultiplier.vcd");
        $dumpvars(0, testbench);
    end
    //stimulus
    initial begin
        clk = 0; start = 0;
        #5;
        for(i = -7; i < 8; i = i+1) begin
            for(j = -8; j < 8; j = j+1) begin
                #79 start = 1; #1 a = i; b = j; #10 start = 0;
            end
        end
        #100 $finish;
    end
    //clock
    initial begin
        clk = 0;
        forever #5 clk = ~clk;
    end
endmodule

Experiment 01/boothMultiplier.vcd
$date
	Mon Aug 12 17:46:29 2019
$end
$version
	Icarus Verilog
$end
$timescale
	1ps
$end
$scope module testbench $end
$var wire 1 ! busy $end
$var wire 8 " ab [7:0] $end
$var reg 4 # a [3:0] $end
$var reg 4 $ b [3:0] $end
$var reg 1 % clk $end
$var reg 1 & start $end
$var integer 32 ' i [31:0] $end
$var integer 32 ( j [31:0] $end
$scope module uut $end
$var wire 1 % clk $end
$var wire 4 ) mc [3:0] $end
$var wire 4 * mp [3:0] $end
$var wire 1 & start $end
$var wire 4 + sum [3:0] $end
$var wire 4 , difference [3:0] $end
$var reg 4 - A [3:0] $end
$var reg 4 . M [3:0] $end
$var reg 4 / Q [3:0] $end
$var reg 1 0 Q_1 $end
$var reg 1 ! busy $end
$var reg 3 1 count [2:0] $end
$var reg 8 2 prod [7:0] $end
$scope module adder $end
$var wire 4 3 a [3:0] $end
$var wire 4 4 b [3:0] $end
$var wire 1 5 cin $end
$var wire 4 6 out [3:0] $end
$upscope $end
$scope module subtracter $end
$var wire 4 7 a [3:0] $end
$var wire 4 8 b [3:0] $end
$var wire 1 9 cin $end
$var wire 4 : out [3:0] $end
$upscope $end
$upscope $end
$upscope $end
$enddefinitions $end
#0
$dumpvars
bx :
19
bx 8
bx 7
bx 6
05
bx 4
bx 3
bx 2
bx 1
x0
bx /
bx .
bx -
bx ,
bx +
bx *
bx )
bx (
bx '
0&
0%
bx $
bx #
bx "
x!
$end
#5000
1!
1%
b11111111111111111111111111111000 (
b11111111111111111111111111111001 '
#10000
0%
#15000
1%
#20000
0%
#25000
1%
#30000
0%
#35000
1%
#40000
0%
#45000
1%
#50000
0%
#55000
1%
#60000
0%
#65000
1%
#70000
0%
#75000
1%
#80000
0%
#84000
1&
#85000
b111 ,
b111 :
b110 8
b0 1
00
b1000 /
b1001 +
b1001 6
b1001 .
b1001 4
b0 -
b0 3
b0 7
b1000 $
b1000 *
b1001 #
b1001 )
1%
#90000
0%
#95000
b1 1
b100 /
1%
b11111111111111111111111111111001 (
0&
#100000
0%
#105000
b10 1
b10 /
1%
#110000
0%
#115000
b11 1
b1 /
1%
#120000
0%
#125000
b100 1
b1100 +
b1100 6
b1010 ,
b1010 :
b11 -
b11 3
b11 7
b1000 /
10
1%
#130000
0%
#135000
b111000 "
b111000 2
0!
b0 1
b111 +
b111 6
b101 ,
b101 :
b1110 -
b1110 3
b1110 7
b100 /
00
1%
#140000
0%
#145000
b1 1
b1000 +
b1000 6
b110 ,
b110 :
b1111 -
b1111 3
b1111 7
b10 /
1!
1%
#150000
0%
#155000
b10 1
b1001 /
1%
#160000
0%
#165000
b11 1
b1100 +
b1100 6
b1010 ,
b1010 :
b11 -
b11 3
b11 7
b100 /
10
1%
#170000
0%
#174000
1&
#175000
b0 1
00
b1001 /
b1001 +
b1001 6
b111 ,
b111 :
b0 -
b0 3
b0 7
b1001 $
b1001 *
1%
#180000
0%
#185000
b1 1
b1100 +
b1100 6
b1010 ,
b1010 :
b11 -
b11 3
b11 7
b1100 /
10
1%
b11111111111111111111111111111010 (
0&
#190000
0%
#195000
b10 1
b111 +
b111 6
b101 ,
b101 :
b1110 -
b1110 3
b1110 7
b110 /
00
1%
#200000
0%
#205000
b11 1
b1000 +
b1000 6
b110 ,
b110 :
b1111 -
b1111 3
b1111 7
b11 /
1%
#210000
0%
#215000
b100 1
b1100 +
b1100 6
b1010 ,
b1010 :
b11 -
b11 3
b11 7
b1 /
10
1%
#220000
0%
#225000
b110001 "
b110001 2
0!
b0 1
b1010 +
b1010 6
b1000 ,
b1000 :
b1 -
b1 3
b1 7
b1000 /
1%
#230000
0%
#235000
b1 1
b110 +
b110 6
b100 ,
b100 :
b1101 -
b1101 3
b1101 7
b100 /
00
1!
1%
#240000
0%
#245000
b10 1
b111 +
b111 6
b101 ,
b101 :
b1110 -
b1110 3
b1110 7
b1010 /
1%
#250000
0%
#255000
b11 1
b1000 +
b1000 6
b110 ,
b110 :
b1111 -
b1111 3
b1111 7
b101 /
1%
#260000
0%
#264000
1&
#265000
b0 1
b1010 /
b1001 +
b1001 6
b111 ,
b111 :
b0 -
b0 3
b0 7
b1010 $
b1010 *
1%
#270000
0%
#275000
b1 1
b101 /
1%
b11111111111111111111111111111011 (
0&
#280000
0%
#285000
b10 1
b1100 +
b1100 6
b1010 ,
b1010 :
b11 -
b11 3
b11 7
b1010 /
10
1%
#290000
0%
#295000
b11 1
b111 +
b111 6
b101 ,
b101 :
b1110 -
b1110 3
b1110 7
b101 /
00
1%
#300000
0%
#305000
b100 1
b1011 +
b1011 6
b1001 ,
b1001 :
b10 -
b10 3
b10 7
b1010 /
10
1%
#310000
0%
#315000
b101010 "
b101010 2
0!
b0 1
b110 +
b110 6
b100 ,
b100 :
b1101 -
b1101 3
b1101 7
b1101 /
00
1%
#320000
0%
#325000
b1 1
b1011 +
b1011 6
b1001 ,
b1001 :
b10 -
b10 3
b10 7
b110 /
10
1!
1%
#330000
0%
#335000
b10 1
b110 +
b110 6
b100 ,
b100 :
b1101 -
b1101 3
b1101 7
b1011 /
00
1%
#340000
0%
#345000
b11 1
b1011 +
b1011 6
b1001 ,
b1001 :
b10 -
b10 3
b10 7
b101 /
10
1%
#350000
0%
#354000
1&
#355000
b0 1
00
b1011 /
b1001 +
b1001 6
b111 ,
b111 :
b0 -
b0 3
b0 7
b1011 $
b1011 *
1%
#360000
0%
#365000
b1 1
b1100 +
b1100 6
b1010 ,
b1010 :
b11 -
b11 3
b11 7
b1101 /
10
1%
b11111111111111111111111111111100 (
0&
#370000
0%
#375000
b10 1
b1010 +
b1010 6
b1000 ,
b1000 :
b1 -
b1 3
b1 7
b1110 /
1%
#380000
0%
#385000
b11 1
b110 +
b110 6
b100 ,
b100 :
b1101 -
b1101 3
b1101 7
b111 /
00
1%
#390000
0%
#395000
b100 1
b1011 +
b1011 6
b1001 ,
b1001 :
b10 -
b10 3
b10 7
b11 /
10
1%
#400000
0%
#405000
b100011 "
b100011 2
0!
b0 1
b1010 +
b1010 6
b1000 ,
b1000 :
b1 -
b1 3
b1 7
b1 /
1%
#410000
0%
#415000
b1 1
b1001 +
b1001 6
b111 ,
b111 :
b0 -
b0 3
b0 7
b1000 /
1!
1%
#420000
0%
#425000
b10 1
b101 +
b101 6
b11 ,
b11 :
b1100 -
b1100 3
b1100 7
b1100 /
00
1%
#430000
0%
#435000
b11 1
b111 +
b111 6
b101 ,
b101 :
b1110 -
b1110 3
b1110 7
b110 /
1%
#440000
0%
#444000
1&
#445000
b0 1
b1100 /
b1001 +
b1001 6
b111 ,
b111 :
b0 -
b0 3
b0 7
b1100 $
b1100 *
1%
#450000
0%
#455000
b1 1
b110 /
1%
b11111111111111111111111111111101 (
0&
#460000
0%
#465000
b10 1
b11 /
1%
#470000
0%
#475000
b11 1
b1100 +
b1100 6
b1010 ,
b1010 :
b11 -
b11 3
b11 7
b1001 /
10
1%
#480000
0%
#485000
b100 1
b1010 +
b1010 6
b1000 ,
b1000 :
b1 -
b1 3
b1 7
b1100 /
1%
#490000
0%
#495000
b11100 "
b11100 2
0!
b0 1
b110 +
b110 6
b100 ,
b100 :
b1101 -
b1101 3
b1101 7
b110 /
00
1%
#500000
0%
#505000
b1 1
b111 +
b111 6
b101 ,
b101 :
b1110 -
b1110 3
b1110 7
b1011 /
1!
1%
#510000
0%
#515000
b10 1
b1011 +
b1011 6
b1001 ,
b1001 :
b10 -
b10 3
b10 7
b1101 /
10
1%
#520000
0%
#525000
b11 1
b1010 +
b1010 6
b1000 ,
b1000 :
b1 -
b1 3
b1 7
b110 /
1%
#530000
0%
#534000
1&
#535000
b0 1
00
b1101 /
b1001 +
b1001 6
b111 ,
b111 :
b0 -
b0 3
b0 7
b1101 $
b1101 *
1%
#540000
0%
#545000
b1 1
b1100 +
b1100 6
b1010 ,
b1010 :
b11 -
b11 3
b11 7
b1110 /
10
1%
b11111111111111111111111111111110 (
0&
#550000
0%
#555000
b10 1
b111 +
b111 6
b101 ,
b101 :
b1110 -
b1110 3
b1110 7
b111 /
00
1%
#560000
0%
#565000
b11 1
b1011 +
b1011 6
b1001 ,
b1001 :
b10 -
b10 3
b10 7
b1011 /
10
1%
#570000
0%
#575000
b100 1
b1010 +
b1010 6
b1000 ,
b1000 :
b1 -
b1 3
b1 7
b101 /
1%
#580000
0%
#585000
b10101 "
b10101 2
0!
b0 1
b1001 +
b1001 6
b111 ,
b111 :
b0 -
b0 3
b0 7
b1010 /
1%
#590000
0%
#595000
b1 1
b101 +
b101 6
b11 ,
b11 :
b1100 -
b1100 3
b1100 7
b1101 /
00
1!
1%
#600000
0%
#605000
b10 1
b1010 +
b1010 6
b1000 ,
b1000 :
b1 -
b1 3
b1 7
b1110 /
10
1%
#610000
0%
#615000
b11 1
b110 +
b110 6
b100 ,
b100 :
b1101 -
b1101 3
b1101 7
b111 /
00
1%
#620000
0%
#624000
1&
#625000
b0 1
b1110 /
b1001 +
b1001 6
b111 ,
b111 :
b0 -
b0 3
b0 7
b1110 $
b1110 *
1%
#630000
0%
#635000
b1 1
b111 /
1%
b11111111111111111111111111111111 (
0&
#640000
0%
#645000
b10 1
b1100 +
b1100 6
b1010 ,
b1010 :
b11 -
b11 3
b11 7
b1011 /
10
1%
#650000
0%
#655000
b11 1
b1010 +
b1010 6
b1000 ,
b1000 :
b1 -
b1 3
b1 7
b1101 /
1%
#660000
0%
#665000
b100 1
b1001 +
b1001 6
b111 ,
b111 :
b0 -
b0 3
b0 7
b1110 /
1%
#670000
0%
#675000
b1110 "
b1110 2
0!
b0 1
b101 +
b101 6
b11 ,
b11 :
b1100 -
b1100 3
b1100 7
b1111 /
00
1%
#680000
0%
#685000
b1 1
b1010 +
b1010 6
b1000 ,
b1000 :
b1 -
b1 3
b1 7
10
1!
1%
#690000
0%
#695000
b10 1
b1001 +
b1001 6
b111 ,
b111 :
b0 -
b0 3
b0 7
1%
#700000
0%
#705000
b11 1
b111 /
1%
#710000
0%
#714000
1&
#715000
b0 1
00
b1111 /
b1111 $
b1111 *
1%
#720000
0%
#725000
b1 1
b1100 +
b1100 6
b1010 ,
b1010 :
b11 -
b11 3
b11 7
10
1%
b0 (
0&
#730000
0%
#735000
b10 1
b1010 +
b1010 6
b1000 ,
b1000 :
b1 -
b1 3
b1 7
1%
#740000
0%
#745000
b11 1
b1001 +
b1001 6
b111 ,
b111 :
b0 -
b0 3
b0 7
1%
#750000
0%
#755000
b100 1
b111 /
1%
#760000
0%
#765000
b111 "
b111 2
0!
b0 1
b11 /
1%
#770000
0%
#775000
b1 1
b1 /
1!
1%
#780000
0%
#785000
b10 1
b0 /
1%
#790000
0%
#795000
b11 1
b101 +
b101 6
b11 ,
b11 :
b1100 -
b1100 3
b1100 7
b1000 /
00
1%
#800000
0%
#804000
1&
#805000
b0 1
b0 /
b1001 +
b1001 6
b111 ,
b111 :
b0 -
b0 3
b0 7
b0 $
b0 *
1%
#810000
0%
#815000
b1 1
1%
b1 (
0&
#820000
0%
#825000
b10 1
1%
#830000
0%
#835000
b11 1
1%
#840000
0%
#845000
b100 1
1%
#850000
0%
#855000
b0 "
b0 2
0!
b0 1
1%
#860000
0%
#865000
b1 1
1!
1%
#870000
0%
#875000
b10 1
1%
#880000
0%
#885000
b11 1
1%
#890000
0%
#894000
1&
#895000
b0 1
b1 /
b1 $
b1 *
1%
#900000
0%
#905000
b1 1
b1100 +
b1100 6
b1010 ,
b1010 :
b11 -
b11 3
b11 7
b1000 /
10
1%
b10 (
0&
#910000
0%
#915000
b10 1
b111 +
b111 6
b101 ,
b101 :
b1110 -
b1110 3
b1110 7
b100 /
00
1%
#920000
0%
#925000
b11 1
b1000 +
b1000 6
b110 ,
b110 :
b1111 -
b1111 3
b1111 7
b10 /
1%
#930000
0%
#935000
b100 1
b1001 /
1%
#940000
0%
#945000
b11111001 "
b11111001 2
0!
b0 1
b1100 +
b1100 6
b1010 ,
b1010 :
b11 -
b11 3
b11 7
b100 /
10
1%
#950000
0%
#955000
b1 1
b111 +
b111 6
b101 ,
b101 :
b1110 -
b1110 3
b1110 7
b10 /
00
1!
1%
#960000
0%
#965000
b10 1
b1000 +
b1000 6
b110 ,
b110 :
b1111 -
b1111 3
b1111 7
b1 /
1%
#970000
0%
#975000
b11 1
b1100 +
b1100 6
b1010 ,
b1010 :
b11 -
b11 3
b11 7
b0 /
10
1%
#980000
0%
#984000
1&
#985000
b0 1
00
b10 /
b1001 +
b1001 6
b111 ,
b111 :
b0 -
b0 3
b0 7
b10 $
b10 *
1%
#990000
0%
#995000
b1 1
b1 /
1%
b11 (
0&
#1000000
0%
#1005000
b10 1
b1100 +
b1100 6
b1010 ,
b1010 :
b11 -
b11 3
b11 7
b1000 /
10
1%
#1010000
0%
#1015000
b11 1
b111 +
b111 6
b101 ,
b101 :
b1110 -
b1110 3
b1110 7
b100 /
00
1%
#1020000
0%
#1025000
b100 1
b1000 +
b1000 6
b110 ,
b110 :
b1111 -
b1111 3
b1111 7
b10 /
1%
#1030000
0%
#1035000
b11110010 "
b11110010 2
0!
b0 1
b1001 /
1%
#1040000
0%
#1045000
b1 1
b1100 +
b1100 6
b1010 ,
b1010 :
b11 -
b11 3
b11 7
b100 /
10
1!
1%
#1050000
0%
#1055000
b10 1
b111 +
b111 6
b101 ,
b101 :
b1110 -
b1110 3
b1110 7
b10 /
00
1%
#1060000
0%
#1065000
b11 1
b1000 +
b1000 6
b110 ,
b110 :
b1111 -
b1111 3
b1111 7
b1 /
1%
#1070000
0%
#1074000
1&
#1075000
b0 1
b11 /
b1001 +
b1001 6
b111 ,
b111 :
b0 -
b0 3
b0 7
b11 $
b11 *
1%
#1080000
0%
#1085000
b1 1
b1100 +
b1100 6
b1010 ,
b1010 :
b11 -
b11 3
b11 7
b1001 /
10
1%
b100 (
0&
#1090000
0%
#1095000
b10 1
b1010 +
b1010 6
b1000 ,
b1000 :
b1 -
b1 3
b1 7
b1100 /
1%
#1100000
0%
#1105000
b11 1
b110 +
b110 6
b100 ,
b100 :
b1101 -
b1101 3
b1101 7
b110 /
00
1%
#1110000
0%
#1115000
b100 1
b111 +
b111 6
b101 ,
b101 :
b1110 -
b1110 3
b1110 7
b1011 /
1%
#1120000
0%
#1125000
b11101011 "
b11101011 2
0!
b0 1
b1011 +
b1011 6
b1001 ,
b1001 :
b10 -
b10 3
b10 7
b1101 /
10
1%
#1130000
0%
#1135000
b1 1
b1010 +
b1010 6
b1000 ,
b1000 :
b1 -
b1 3
b1 7
b110 /
1!
1%
#1140000
0%
#1145000
b10 1
b110 +
b110 6
b100 ,
b100 :
b1101 -
b1101 3
b1101 7
b11 /
00
1%
#1150000
0%
#1155000
b11 1
b1011 +
b1011 6
b1001 ,
b1001 :
b10 -
b10 3
b10 7
b1 /
10
1%
#1160000
0%
#1164000
1&
#1165000
b0 1
00
b100 /
b1001 +
b1001 6
b111 ,
b111 :
b0 -
b0 3
b0 7
b100 $
b100 *
1%
#1170000
0%
#1175000
b1 1
b10 /
1%
b101 (
0&
#1180000
0%
#1185000
b10 1
b1 /
1%
#1190000
0%
#1195000
b11 1
b1100 +
b1100 6
b1010 ,
b1010 :
b11 -
b11 3
b11 7
b1000 /
10
1%
#1200000
0%
#1205000
b100 1
b111 +
b111 6
b101 ,
b101 :
b1110 -
b1110 3
b1110 7
b100 /
00
1%
#1210000
0%
#1215000
b11100100 "
b11100100 2
0!
b0 1
b1000 +
b1000 6
b110 ,
b110 :
b1111 -
b1111 3
b1111 7
b10 /
1%
#1220000
0%
#1225000
b1 1
b1001 /
1!
1%
#1230000
0%
#1235000
b10 1
b1100 +
b1100 6
b1010 ,
b1010 :
b11 -
b11 3
b11 7
b100 /
10
1%
#1240000
0%
#1245000
b11 1
b111 +
b111 6
b101 ,
b101 :
b1110 -
b1110 3
b1110 7
b10 /
00
1%
#1250000
0%
#1254000
1&
#1255000
b0 1
b101 /
b1001 +
b1001 6
b111 ,
b111 :
b0 -
b0 3
b0 7
b101 $
b101 *
1%
#1260000
0%
#1265000
b1 1
b1100 +
b1100 6
b1010 ,
b1010 :
b11 -
b11 3
b11 7
b1010 /
10
1%
b110 (
0&
#1270000
0%
#1275000
b10 1
b111 +
b111 6
b101 ,
b101 :
b1110 -
b1110 3
b1110 7
b101 /
00
1%
#1280000
0%
#1285000
b11 1
b1011 +
b1011 6
b1001 ,
b1001 :
b10 -
b10 3
b10 7
b1010 /
10
1%
#1290000
0%
#1295000
b100 1
b110 +
b110 6
b100 ,
b100 :
b1101 -
b1101 3
b1101 7
b1101 /
00
1%
#1300000
0%
#1305000
b11011101 "
b11011101 2
0!
b0 1
b1011 +
b1011 6
b1001 ,
b1001 :
b10 -
b10 3
b10 7
b110 /
10
1%
#1310000
0%
#1315000
b1 1
b110 +
b110 6
b100 ,
b100 :
b1101 -
b1101 3
b1101 7
b1011 /
00
1!
1%
#1320000
0%
#1325000
b10 1
b1011 +
b1011 6
b1001 ,
b1001 :
b10 -
b10 3
b10 7
b101 /
10
1%
#1330000
0%
#1335000
b11 1
b1010 +
b1010 6
b1000 ,
b1000 :
b1 -
b1 3
b1 7
b10 /
1%
#1340000
0%
#1344000
1&
#1345000
b0 1
00
b110 /
b1001 +
b1001 6
b111 ,
b111 :
b0 -
b0 3
b0 7
b110 $
b110 *
1%
#1350000
0%
#1355000
b1 1
b11 /
1%
b111 (
0&
#1360000
0%
#1365000
b10 1
b1100 +
b1100 6
b1010 ,
b1010 :
b11 -
b11 3
b11 7
b1001 /
10
1%
#1370000
0%
#1375000
b11 1
b1010 +
b1010 6
b1000 ,
b1000 :
b1 -
b1 3
b1 7
b1100 /
1%
#1380000
0%
#1385000
b100 1
b110 +
b110 6
b100 ,
b100 :
b1101 -
b1101 3
b1101 7
b110 /
00
1%
#1390000
0%
#1395000
b11010110 "
b11010110 2
0!
b0 1
b111 +
b111 6
b101 ,
b101 :
b1110 -
b1110 3
b1110 7
b1011 /
1%
#1400000
0%
#1405000
b1 1
b1011 +
b1011 6
b1001 ,
b1001 :
b10 -
b10 3
b10 7
b1101 /
10
1!
1%
#1410000
0%
#1415000
b10 1
b1010 +
b1010 6
b1000 ,
b1000 :
b1 -
b1 3
b1 7
b110 /
1%
#1420000
0%
#1425000
b11 1
b110 +
b110 6
b100 ,
b100 :
b1101 -
b1101 3
b1101 7
b11 /
00
1%
#1430000
0%
#1434000
1&
#1435000
b0 1
b111 /
b1001 +
b1001 6
b111 ,
b111 :
b0 -
b0 3
b0 7
b111 $
b111 *
1%
#1440000
0%
#1445000
b1 1
b1100 +
b1100 6
b1010 ,
b1010 :
b11 -
b11 3
b11 7
b1011 /
10
1%
b11111111111111111111111111111010 '
b11111111111111111111111111111000 (
0&
#1450000
0%
#1455000
b10 1
b1010 +
b1010 6
b1000 ,
b1000 :
b1 -
b1 3
b1 7
b1101 /
1%
#1460000
0%
#1465000
b11 1
b1001 +
b1001 6
b111 ,
b111 :
b0 -
b0 3
b0 7
b1110 /
1%
#1470000
0%
#1475000
b100 1
b101 +
b101 6
b11 ,
b11 :
b1100 -
b1100 3
b1100 7
b1111 /
00
1%
#1480000
0%
#1485000
b11001111 "
b11001111 2
0!
b0 1
b1010 +
b1010 6
b1000 ,
b1000 :
b1 -
b1 3
b1 7
10
1%
#1490000
0%
#1495000
b1 1
b1001 +
b1001 6
b111 ,
b111 :
b0 -
b0 3
b0 7
1!
1%
#1500000
0%
#1505000
b10 1
b111 /
1%
#1510000
0%
#1515000
b11 1
b11 /
1%
#1520000
0%
#1524000
1&
#1525000
b110 ,
b110 :
b101 8
b0 1
00
b1000 /
b1010 +
b1010 6
b1010 .
b1010 4
b1000 $
b1000 *
b1010 #
b1010 )
1%
#1530000
0%
#1535000
b1 1
b100 /
1%
b11111111111111111111111111111001 (
0&
#1540000
0%
#1545000
b10 1
b10 /
1%
#1550000
0%
#1555000
b11 1
b1 /
1%
#1560000
0%
#1565000
b100 1
b1101 +
b1101 6
b1001 ,
b1001 :
b11 -
b11 3
b11 7
b0 /
10
1%
#1570000
0%
#1575000
b110000 "
b110000 2
0!
b0 1
b1000 +
b1000 6
b100 ,
b100 :
b1110 -
b1110 3
b1110 7
b1000 /
00
1%
#1580000
0%
#1585000
b1 1
b1001 +
b1001 6
b101 ,
b101 :
b1111 -
b1111 3
b1111 7
b100 /
1!
1%
#1590000
0%
#1595000
b10 1
b1010 /
1%
#1600000
0%
#1605000
b11 1
b1101 /
1%
#1610000
0%
#1614000
1&
#1615000
b0 1
b1001 /
b1010 +
b1010 6
b110 ,
b110 :
b0 -
b0 3
b0 7
b1001 $
b1001 *
1%
#1620000
0%
#1625000
b1 1
b1101 +
b1101 6
b1001 ,
b1001 :
b11 -
b11 3
b11 7
b100 /
10
1%
b11111111111111111111111111111010 (
0&
#1630000
0%
#1635000
b10 1
b1000 +
b1000 6
b100 ,
b100 :
b1110 -
b1110 3
b1110 7
b1010 /
00
1%
#1640000
0%
#1645000
b11 1
b1001 +
b1001 6
b101 ,
b101 :
b1111 -
b1111 3
b1111 7
b101 /
1%
#1650000
0%
#1655000
b100 1
b1100 +
b1100 6
b1000 ,
b1000 :
b10 -
b10 3
b10 7
b1010 /
10
1%
#1660000
0%
#1665000
b101010 "
b101010 2
0!
b0 1
b1000 +
b1000 6
b100 ,
b100 :
b1110 -
b1110 3
b1110 7
b101 /
00
1%
#1670000
0%
#1675000
b1 1
b1100 +
b1100 6
b1000 ,
b1000 :
b10 -
b10 3
b10 7
b10 /
10
1!
1%
#1680000
0%
#1685000
b10 1
b1000 +
b1000 6
b100 ,
b100 :
b1110 -
b1110 3
b1110 7
b1 /
00
1%
#1690000
0%
#1695000
b11 1
b1100 +
b1100 6
b1000 ,
b1000 :
b10 -
b10 3
b10 7
b0 /
10
1%
#1700000
0%
#1704000
1&
#1705000
b0 1
00
b1010 /
b1010 +
b1010 6
b110 ,
b110 :
b0 -
b0 3
b0 7
b1010 $
b1010 *
1%
#1710000
0%
#1715000
b1 1
b101 /
1%
b11111111111111111111111111111011 (
0&
#1720000
0%
#1725000
b10 1
b1101 +
b1101 6
b1001 ,
b1001 :
b11 -
b11 3
b11 7
b10 /
10
1%
#1730000
0%
#1735000
b11 1
b1000 +
b1000 6
b100 ,
b100 :
b1110 -
b1110 3
b1110 7
b1001 /
00
1%
#1740000
0%
#1745000
b100 1
b1100 +
b1100 6
b1000 ,
b1000 :
b10 -
b10 3
b10 7
b100 /
10
1%
#1750000
0%
#1755000
b100100 "
b100100 2
0!
b0 1
b1000 +
b1000 6
b100 ,
b100 :
b1110 -
b1110 3
b1110 7
b10 /
00
1%
#1760000
0%
#1765000
b1 1
b1001 +
b1001 6
b101 ,
b101 :
b1111 -
b1111 3
b1111 7
b1 /
1!
1%
#1770000
0%
#1775000
b10 1
b1100 +
b1100 6
b1000 ,
b1000 :
b10 -
b10 3
b10 7
b1000 /
10
1%
#1780000
0%
#1785000
b11 1
b1000 +
b1000 6
b100 ,
b100 :
b1110 -
b1110 3
b1110 7
b100 /
00
1%
#1790000
0%
#1794000
1&
#1795000
b0 1
b1011 /
b1010 +
b1010 6
b110 ,
b110 :
b0 -
b0 3
b0 7
b1011 $
b1011 *
1%
#1800000
0%
#1805000
b1 1
b1101 +
b1101 6
b1001 ,
b1001 :
b11 -
b11 3
b11 7
b101 /
10
1%
b11111111111111111111111111111100 (
0&
#1810000
0%
#1815000
b10 1
b1011 +
b1011 6
b111 ,
b111 :
b1 -
b1 3
b1 7
b1010 /
1%
#1820000
0%
#1825000
b11 1
b111 +
b111 6
b11 ,
b11 :
b1101 -
b1101 3
b1101 7
b1101 /
00
1%
#1830000
0%
#1835000
b100 1
b1011 +
b1011 6
b111 ,
b111 :
b1 -
b1 3
b1 7
b1110 /
10
1%
#1840000
0%
#1845000
b11110 "
b11110 2
0!
b0 1
b111 +
b111 6
b11 ,
b11 :
b1101 -
b1101 3
b1101 7
b1111 /
00
1%
#1850000
0%
#1855000
b1 1
b1011 +
b1011 6
b111 ,
b111 :
b1 -
b1 3
b1 7
10
1!
1%
#1860000
0%
#1865000
b10 1
b1010 +
b1010 6
b110 ,
b110 :
b0 -
b0 3
b0 7
1%
#1870000
0%
#1875000
b11 1
b111 /
1%
#1880000
0%
#1884000
1&
#1885000
b0 1
00
b1100 /
b1100 $
b1100 *
1%
#1890000
0%
#1895000
b1 1
b110 /
1%
b11111111111111111111111111111101 (
0&
#1900000
0%
#1905000
b10 1
b11 /
1%
#1910000
0%
#1915000
b11 1
b1101 +
b1101 6
b1001 ,
b1001 :
b11 -
b11 3
b11 7
b1 /
10
1%
#1920000
0%
#1925000
b100 1
b1011 +
b1011 6
b111 ,
b111 :
b1 -
b1 3
b1 7
b1000 /
1%
#1930000
0%
#1935000
b11000 "
b11000 2
0!
b0 1
b111 +
b111 6
b11 ,
b11 :
b1101 -
b1101 3
b1101 7
b1100 /
00
1%
#1940000
0%
#1945000
b1 1
b1000 +
b1000 6
b100 ,
b100 :
b1110 -
b1110 3
b1110 7
b1110 /
1!
1%
#1950000
0%
#1955000
b10 1
b1001 +
b1001 6
b101 ,
b101 :
b1111 -
b1111 3
b1111 7
b111 /
1%
#1960000
0%
#1965000
b11 1
b1100 +
b1100 6
b1000 ,
b1000 :
b10 -
b10 3
b10 7
b1011 /
10
1%
#1970000
0%
#1974000
1&
#1975000
b0 1
00
b1101 /
b1010 +
b1010 6
b110 ,
b110 :
b0 -
b0 3
b0 7
b1101 $
b1101 *
1%
#1980000
0%
#1985000
b1 1
b1101 +
b1101 6
b1001 ,
b1001 :
b11 -
b11 3
b11 7
b110 /
10
1%
b11111111111111111111111111111110 (
0&
#1990000
0%
#1995000
b10 1
b1000 +
b1000 6
b100 ,
b100 :
b1110 -
b1110 3
b1110 7
b1011 /
00
1%
#2000000
0%
#2005000
b11 1
b1100 +
b1100 6
b1000 ,
b1000 :
b10 -
b10 3
b10 7
b101 /
10
1%
#2010000
0%
#2015000
b100 1
b1011 +
b1011 6
b111 ,
b111 :
b1 -
b1 3
b1 7
b10 /
1%
#2020000
0%
#2025000
b10010 "
b10010 2
0!
b0 1
b111 +
b111 6
b11 ,
b11 :
b1101 -
b1101 3
b1101 7
b1001 /
00
1%
#2030000
0%
#2035000
b1 1
b1011 +
b1011 6
b111 ,
b111 :
b1 -
b1 3
b1 7
b1100 /
10
1!
1%
#2040000
0%
#2045000
b10 1
b111 +
b111 6
b11 ,
b11 :
b1101 -
b1101 3
b1101 7
b1110 /
00
1%
#2050000
0%
#2055000
b11 1
b1000 +
b1000 6
b100 ,
b100 :
b1110 -
b1110 3
b1110 7
b1111 /
1%
#2060000
0%
#2064000
1&
#2065000
b0 1
b1110 /
b1010 +
b1010 6
b110 ,
b110 :
b0 -
b0 3
b0 7
b1110 $
b1110 *
1%
#2070000
0%
#2075000
b1 1
b111 /
1%
b11111111111111111111111111111111 (
0&
#2080000
0%
#2085000
b10 1
b1101 +
b1101 6
b1001 ,
b1001 :
b11 -
b11 3
b11 7
b11 /
10
1%
#2090000
0%
#2095000
b11 1
b1011 +
b1011 6
b111 ,
b111 :
b1 -
b1 3
b1 7
b1001 /
1%
#2100000
0%
#2105000
b100 1
b1010 +
b1010 6
b110 ,
b110 :
b0 -
b0 3
b0 7
b1100 /
1%
#2110000
0%
#2115000
b1100 "
b1100 2
0!
b0 1
b111 +
b111 6
b11 ,
b11 :
b1101 -
b1101 3
b1101 7
b110 /
00
1%
#2120000
0%
#2125000
b1 1
b1000 +
b1000 6
b100 ,
b100 :
b1110 -
b1110 3
b1110 7
b1011 /
1!
1%
#2130000
0%
#2135000
b10 1
b1100 +
b1100 6
b1000 ,
b1000 :
b10 -
b10 3
b10 7
b101 /
10
1%
#2140000
0%
#2145000
b11 1
b1011 +
b1011 6
b111 ,
b111 :
b1 -
b1 3
b1 7
b10 /
1%
